wiz_utils/__init__.py
wiz_utils/array_utils.py
wiz_utils/string_utils.py
wiz_utils-1.0.2.dist-info/METADATA
wiz_utils-1.0.2.dist-info/RECORD
wiz_utils-1.0.2.dist-info/WHEEL
wiz_utils-1.0.2.dist-info/top_level.txt
